pythonmentor/__init__.py
pythonmentor/core.py
pythonmentor/dir/__init__.py
pythonmentor/dir/checker.py
pythonmentor/extractor/__init__.py
pythonmentor/extractor/unzipper.py
pythonmentor/models/__init__.py
pythonmentor/models/gemini.py
pythonmentor/models/model.py
pythonmentor/processors/__init__.py
pythonmentor/processors/processor.py
ipythonmentor-0.5.0.dist-info/METADATA
ipythonmentor-0.5.0.dist-info/WHEEL
ipythonmentor-0.5.0.dist-info/top_level.txt
ipythonmentor-0.5.0.dist-info/RECORD
