Metadata-Version: 2.4
Name: IPythonMentor
Version: 0.5.0
Summary: Grade Python submissions with Gemini feedback.
Requires-Python: >=3.9
Requires-Dist: google-genai>=0.4.0
Dynamic: requires-dist
Dynamic: requires-python
Dynamic: summary
